<?xml version="1.0"?>
<Results version="1.0">
<ReportNode type="testrun">
<ReportNode type="Iteration">
<ReportNode type="Action">
<ReportNode type="Step">
<Data>
    <Name>Expected ')'</Name>
    <ErrorText>Expected ')'</ErrorText>
    <Description>&lt;BR/&gt;Line (2): &amp;quot;print dateadd(&amp;quot;d&amp;quot; 3 &amp;quot;31-dec-2023&amp;quot;)&amp;quot;.</Description>
    <StartTime>2023-03-03 10:21:56</StartTime>
    <Result>Failed</Result>
    <Extension>
      <IconKey>542307e0dc114a7aa29a554df2ceedd9</IconKey>
      <IsPlainTextNodeName>True</IsPlainTextNodeName>
      <MergeIsErrorIcon>True</MergeIsErrorIcon>
    </Extension>
  </Data>
</ReportNode>
<ReportNode type="Step">
<Data>
    <Name>Stop Run</Name>
    <Description>Run stopped by user.</Description>
    <StartTime>2023-03-03 10:21:59</StartTime>
    <Result>Information</Result>
    <Extension>
      <IconKey>f8ff5a36414240b993c8f4c02f991a01</IconKey>
      <IsPlainTextNodeName>True</IsPlainTextNodeName>
    </Extension>
  </Data>
</ReportNode>
<Data>
    <Name>Action1</Name>
    <Description />
    <StartTime>2023-03-03 10:21:56</StartTime>
    <Duration>3</Duration>
    <Result>Failed</Result>
    <InputParameters />
    <Extension>
      <IconKey>325fe6cdf3b74326a443da91ed5f2642</IconKey>
      <IsPlainTextNodeName>True</IsPlainTextNodeName>
    </Extension>
  </Data>
</ReportNode>
<Data>
    <Name>Action0</Name>
    <Description />
    <StartTime>2023-03-03 10:21:56</StartTime>
    <Duration>3</Duration>
    <Result>Failed</Result>
    <Extension>
      <IconKey>71043748d1824a35b350ad9b802b5f61</IconKey>
      <IsPlainTextNodeName>True</IsPlainTextNodeName>
    </Extension>
    <Index>1</Index>
    <TestedApplications />
  </Data>
</ReportNode>
<Data>
    <Name>GUITest9</Name>
    <ToolName>HPE Unified Functional Testing</ToolName>
    <ToolVersion>14.03</ToolVersion>
    <Description />
    <StartTime>2023-03-03 10:21:53</StartTime>
    <Duration>6</Duration>
    <Result>Failed</Result>
    <InputParameters />
    <Extension>
      <IconKey>03999c852be2407bba16d373712e9673</IconKey>
      <IsPlainTextNodeName>True</IsPlainTextNodeName>
    </Extension>
    <Environment>
      <Timezone>+05:30:00</Timezone>
      <Locale>English (India)</Locale>
      <User>Administrator</User>
      <CpuInfo>Intel(R) Xeon(R) CPU E5-2696 v2 @ 2.50GHz</CpuInfo>
      <NumberOfCores>4</NumberOfCores>
      <TotalMemory>16383</TotalMemory>
      <HostName>WINDOWS-UNR7VLH</HostName>
      <OSInfo>Windows 10</OSInfo>
    </Environment>
    <TestedApplications />
    <Links>
      <Link type="DataTable" reference="Default.xls" displayname="Default Data Table" />
    </Links>
  </Data>
</ReportNode>
<GeneralInfo>
    <ResultName>Res1</ResultName>
    <RunStartTime>2023-03-03 10:21:53</RunStartTime>
    <Timezone>+05:30:00</Timezone>
    <OrchestrationToolName>HPE Unified Functional Testing</OrchestrationToolName>
    <OrchestrationToolVersion>14.03</OrchestrationToolVersion>
  </GeneralInfo>
</Results>